fe25519/__init__.py
fe25519/fe25519.py
fe25519-1.5.0.dist-info/LICENSE
fe25519-1.5.0.dist-info/METADATA
fe25519-1.5.0.dist-info/WHEEL
fe25519-1.5.0.dist-info/top_level.txt
fe25519-1.5.0.dist-info/RECORD
