Metadata-Version: 2.1
Name: fe25519
Version: 1.5.0
Summary: Pure-Python data structure for working with Ed25519 (and Ristretto) field elements and operations.
Author: Andrei Lapets
Author-email: a@lapets.io
License: MIT
Project-URL: Repository, https://github.com/nthparty/fe25519
Project-URL: Documentation, https://fe25519.readthedocs.io
Requires-Python: >=3.7
Provides-Extra: docs
Provides-Extra: test
Provides-Extra: lint
Provides-Extra: coveralls
Provides-Extra: publish
License-File: LICENSE
